{
  "name": "1",
  "children": 
    [
      {
      "name": "Universal - length - motion - flow - flove - _ - create - ether - god - end",
      "children": [
          {
            "name": "1.1",
            "children": [
              { 
                "name": "Vital - infinite - function - coherence - full - _ - destiny - limbo - alert - finite - "
              }
            ]
          },
          {
            "name": "1.2",
            "children": [
              { 
                "name": "Intentional - focus - enigma - flirt - alive - _ - diversity - will - karma - chaos - "  
              }
            ]
          },
          {
            "name": "1.3",
            "children": [
              {
                "name": " - Architectural - reciprocity - scalar - superposition - supersimmetry - _ - vortex - omniverse - multiverse - singularity - "
              }
            ]
          }
        ]
      }
    ]
  }
